README.md
setup.py
org_rw/__init__.py
org_rw/dom.py
org_rw/org_rw.py
org_rw/types.py
org_rw/utils.py
org_rw.egg-info/PKG-INFO
org_rw.egg-info/SOURCES.txt
org_rw.egg-info/dependency_links.txt
org_rw.egg-info/top_level.txt
org_rw.egg-info/zip-safe