Metadata-Version: 2.1
Name: org-rw
Version: 0.0.2
Summary: Library to de/serialize org-files and manipulate them.
Author: kenkeiras
Author-email: kenkeiras@codigoparallevar.com
License: Apache License 2.0
